[{
  "_id": {
    "$oid": "65f009a92fb55179008766b3"
  },
  "id": 1,
  "name": " Laptop Asus TUF Gaming",
  "price": 16000000,
  "categoryId": 1,
  "img": "1.jpeg",
  "description": "  laptop Asus TUF Gaming F15 FX506HF là một trong những lựa chọn tuyệt vời cho các game thủ và những người dùng làm việc đa tác vụ hoặc liên quan đến đồ họa, kỹ thuật."
},
{
  "_id": {
    "$oid": "65f009a92fb55179008766b4"
  },
  "id": 2,
  "name": "Iphone 15 Pro Max",
  "price": 31000000,
  "categoryId": 2,
  "img": "2.jpeg",
  "description": "Thiết kế hiện đại, dung lượng khủng"
},
{
  "_id": {
    "$oid": "65f009a92fb55179008766b5"
  },
  "id": 3,
  "name": "Chuột Bluetooth Silent Logitech M240 ",
  "price": 320000,
  "categoryId": 3,
  "img": "3.jpeg",
  "description": "Chuột Bluetooth Silent Logitech M240 với kiểu dáng gọn gàng, gam màu đẹp mắt, kích thước vừa vặn tay cầm, kết nối ổn định cùng độ nhạy khá cao, hứa hẹn mang đến cho bạn những trải nghiệm tuyệt vời."
},
{
  "_id": {
    "$oid": "65f009a92fb55179008766b6"
  },
  "id": 4,
  "name": "Laptop HP Pavilion",
  "price": 17900000,
  "categoryId": 1,
  "img": "4.jpeg",
  "description": "Laptop HP Pavilion 15 eg2062TX i5 1235U (7C0W7PA) mang phong cách thiết kế đơn giản mà thanh lịch, hiệu năng xử lý mạnh mẽ từ card đồ họa rời MX. Chiếc laptop học tập - văn phòng này sẽ đáp ứng đầy đủ mọi nhu cầu làm việc đồ hoạ, sáng tạo và giải trí đa phương tiện của người dùng."
},
{
  "_id": {
    "$oid": "65f009a92fb55179008766b7"
  },
  "id": 5,
  "name": "Vivo Y17s",
  "price": 3400000,
  "categoryId": 2,
  "img": "5.jpeg",
  "description": " vivo Y17s (4GB/64GB) là một sản phẩm của vivo trong dòng Y được bán chính hãng tại Việt Nam, thu hút được nhiều người dùng bởi giá bán rẻ nhưng cấu hình ổn trong phân khúc, những điểm nổi bật có thể kể đến như: Vi xử lý MediaTek Helio G85, camera 50 MP và pin 5000 mAh."
},
{
  "_id": {
    "$oid": "65f009a92fb55179008766b8"
  },
  "id": 6,
  "name": "Laptop Apple MacBook Pro",
  "price": 31000000,
  "categoryId": 1,
  "img": "6.jpeg",
  "description": "Sở hữu thiết kế thanh lịch, sang trọng cùng hiệu năng vượt trội đến từ bộ vi xử lý Apple M2 tân tiến, Macbook Pro M2 hứa hẹn sẽ đáp ứng hoàn hảo cho người dùng sáng tạo, phục vụ tốt cho các nhu cầu thiết kế đồ họa nâng cao."
},
{
  "_id": {
    "$oid": "65f1afbb97ebc5e1ad8a8fbf"
  },
  "id": 7,
  "name": "Điện thoại iPhone 15 Plus 128GB ",
  "price": 23580000,
  "categoryId": 2,
  "img": "7.jpg",
  "description": "iPhone 15 Plus là thiết bị mới nhất của Apple với nhiều tính năng nổi bật"
},
{
  "_id": {
    "$oid": "65f1b43a0c4500d98ed1a6ac"
  },
  "id": 8,
  "name": "Laptop Asus TUF Gaming",
  "price": 16900000,
  "categoryId": 1,
  "img": "8.jpg",
  "description": "laptop chiến game đến từ nhà Asus mang diện mạo cực chất"
},
{
  "_id": {
    "$oid": "65f1b4a347333f6f0f7346eb"
  },
  "id": 9,
  "name": "Laptop Lenovo Ideapad",
  "price": 13190000,
  "categoryId": 1,
  "img": "9.jpg",
  "description": "mang phong cách thiết kế hiện đại kết hợp cùng hiệu năng mạnh mẽ từ bộ vi xử lý Intel Gen 12"
},
{
  "_id": {
    "$oid": "65f1b4fabb727973ac64d16b"
  },
  "id": 10,
  "name": "Điện thoại Samsung Galaxy S24 Ultra",
  "price": 32450000,
  "categoryId": 2,
  "img": "10.jpg",
  "description": "mẫu điện thoại cao cấp được ra mắt vào đầu năm 2024, sản phẩm tiếp tục kế thừa và cải tiến từ thế hệ trước"
},
{
  "_id": {
    "$oid": "65f1b5488ad302dbe0535d72"
  },
  "id": 11,
  "name": "Chuột Có Dây Gaming Zadez G-611M",
  "price": 250000,
  "categoryId": 3,
  "img": "11.jpg",
  "description": "sở hữu thiết kế công thái học vừa vặn, êm tay, chuột có độ phân giải cao lên đến 7200 DPI cho các game thủ thao tác nhanh nhạy, chính xác, đem đến trải nghiệm sử dụng tuyệt vời."
},
{
  "_id": {
    "$oid": "65f1b5a50fcffa11ee3c6cee"
  },
  "id": 12,
  "name": "Laptop MSI Modern",
  "price": 12900000,
  "categoryId": 1,
  "img": "12.jpg",
  "description": "là sự lựa chọn lý tưởng để đồng hành cùng với các bạn tân sinh viên hay thậm chí là nhân viên văn phòng"
},
{
  "_id": {
    "$oid": "65f1b60c8446c30a584e2624"
  },
  "id": 13,
  "name": "Điện thoại OPPO A57 128GB ",
  "price": 3890000,
  "categoryId": 2,
  "img": "13.jpg",
  "description": "Khác với mẫu A57 5G đã được ra mắt trước đó, điện thoại dòng A mới có màn hình HD+, camera chính 13 MP và pin 5000 mAh."
},
{
  "_id": {
    "$oid": "65f1b6be1d798b21373818e7"
  },
  "id": 14,
  "name": "Laptop Acer Nitro 5",
  "price": 22900000,
  "categoryId": 1,
  "img": "14.jpg",
  "description": "khi trang bị bộ vi xử lý Intel Gen 12 đầy mạnh mẽ cùng phong cách thiết kế đậm chất “mãnh hổ”"
}]